but/__init__.py
but/app.py
but/args.py
but/argtypes.py
but/cli_modules.py
but/lazy.py
but/singleton.py
but/store.py
but/archive/__init__.py
but/archive/asar.py
but/binaries/__init__.py
but/external/__init__.py
but/external/ansi.py
but/external/cli.py
but/external/external_executable.py
but/external/node_modules.py
but/html/__init__.py
but/html/parser.py
but/http/__init__.py
but/http/server.py
but/http/update_useragents.py
but/http/useragent.py
but/http/useragents.json
but/scripts/__init__.py
but/scripts/batch.py
but/scripts/echo.py
but/scripts/fetch_hls.py
but/template/__init__.py
but/template/render.py
but/test/__init__.py
but/test/test_ansi.py
but/test/test_asar.py
but/test/test_html.py
but/test/test_lazy.py
but/test/test_singleton.py
but/test/test_template.py
but/watch/__init__.py
but/watch/watch_files.py
but-0.1.3.dist-info/LICENSE
but-0.1.3.dist-info/METADATA
but-0.1.3.dist-info/WHEEL
but-0.1.3.dist-info/entry_points.txt
but-0.1.3.dist-info/top_level.txt
but-0.1.3.dist-info/RECORD
