Metadata-Version: 2.1
Name: but
Version: 0.1.3
Summary: I tried to think of a clever name, but
License: MIT+Ethics License
Requires-Python: >=3.12
License-File: LICENSE
Requires-Dist: beautifulsoup4 ==4.12.3
Requires-Dist: Django ==5.0.4
Requires-Dist: html5lib ==1.1
Requires-Dist: httpx ==0.27.0
Requires-Dist: sh40-slate ==0.7.0
Requires-Dist: sh40-zenith ==0.6.0
Requires-Dist: watchfiles ==0.21.0
